{
    "display_leader_id": "putin_vladimir",
    "display_ideology_id": "sovereign_democracy",
    "ruling_party_id": "united_russia",
    "active_national_focus_id": "autumn_2003_h23_main",
    "active_national_spirit_ids": [
        "fortress_state", "near_abroad_policy", "national_projects_infrastructure",
        "reindustrialization_opk_tech_sovereignty", "divided_society", "systemic_corruption",
        "oil_gas_rent_stabilization_fund", "sovereign_economy", "social_initiatives_family_support",
        "russian_dream_culture_identity", "soft_power_russia_abroad", "moscow_advance"
    ],
    "balance_value": 6,
    "advisors_selected": {
        "advisor_prime_minister": "kasyanov_mikhail",
        "advisor_foreign_affairs": "ivanov_igor_s",
        "advisor_finance": "kudrin_alexey",
        "advisor_defense": "ivanov_sergey_b",
        "advisor_internal_affairs": "gryzlov_boris",
        "advisor_fsb_director": "kovalev_oleg",
        "advisor_svr_director": "lebedev_sergey_n",
        "advisor_justice": "chaika_yuri",
        "advisor_economic_development": "gref_german",
        "advisor_industry_trade": "klebanov_ilya",
        "advisor_energy": "yusufov_igor",
        "advisor_health": "shevchenko_yuri_l",
        "advisor_labor_social": "pochinok_alexander",
        "advisor_education": "filippov_vladimir_m",
        "advisor_culture": "shvydkoy_mikhail",
        "advisor_digital_media": "lesin_mikhail_y"
    },
    "corporations_selected": {
        "corporation_slot_1": "gazprom",
        "corporation_slot_2": "lukoil",
        "corporation_slot_3": "yukos",
        "corporation_slot_4": "surgutneftegaz",
        "corporation_slot_5": "rao_ees",
        "corporation_slot_6": "norilsk_nickel",
        "corporation_slot_7": "rusal",
        "corporation_slot_8": "severstal",
        "corporation_slot_9": "avtovaz",
        "corporation_slot_10": "rostech_concept",
        "corporation_slot_11": "rosoboronprom_concept",
        "corporation_slot_12": "rosoboronexport",
        "corporation_slot_13": "sberbank",
        "corporation_slot_14": "alpha_bank",
        "corporation_slot_15": "vtb",
        "corporation_slot_16": "ingosstrakh",
        "corporation_slot_17": "mts",
        "corporation_slot_18": "vympelcom",
        "corporation_slot_19": "svyazinvest",
        "corporation_slot_20": "channel_one_ort",
        "corporation_slot_21": "rzd_oao",
        "corporation_slot_22": "aeroflot",
        "corporation_slot_23": "magnit",
        "corporation_slot_24": "wimm_bill_dann"
    },
    "constitutional_principles_selected_options": {
        "form_of_government": "super_presidential_republic",
        "human_rights": "formal_observance",
        "voting_system": "universal_referendums_allowed",
        "state_sovereignty": "integrity_no_secession",
        "administrative_structure": "pseudo_federation",
        "citizenship": "jus_soli_inalienable_native",
        "social_model": "social_state_declared",
        "economic_freedoms": "free_market_regulated",
        "natural_resources_management": "mixed_ownership_resources",
        "separation_of_powers": "formal_separation_executive_dominance",
        "governing_bodies": "president_bicameral_gov_courts",
        "local_self_government": "allowed_limited_autonomy",
        "political_system": "multi_party_dominant",
        "status_of_religion": "secular_state",
        "international_law_priority": "constitution_priority",
        "constitution_amendment_core": "high_complexity_core_amendment"
    },
    "development_areas_state": {
        "education": { "current_level_id": "edu_level_2", "current_progress": 65 },
        "healthcare": { "current_level_id": "hc_level_2", "current_progress": 49 },
        "welfare": { "current_level_id": "wel_level_2", "current_progress": 23 },
        "agriculture": { "current_level_id": "agr_level_1", "current_progress": 90 },
        "industry": { "current_level_id": "ind_level_2", "current_progress": 73 },
        "internal_security": { "current_level_id": "isec_level_2", "current_progress": 12 },
        "military_might": { "current_level_id": "mil_level_2", "current_progress": 90 },
        "social_development": { "current_level_id": "soc_dev_level_1", "current_progress": 25 }
    }
}